[
  {
    "id": "bartel_2021_autonomous_design",
    "source_type": "journal_article",
    "title": "Toward autonomous design and synthesis of novel inorganic materials",
    "authors": "Bartel, C.J.",
    "year": 2021,
    "doi": "10.1039/d1mh00495f",
    "abstract": null,
    "added_at": "2026-04-06T23:47:14.287488+00:00",
    "added_by": "seed_loader"
  },
  {
    "id": "deng_2023_chgnet",
    "source_type": "journal_article",
    "title": "CHGNet as a pretrained universal neural network potential for charge-informed atomistic modelling",
    "authors": "Deng, B., Zhong, P., Jun, K., Riebesell, J., Han, K., Bartel, C.J., Ceder, G.",
    "year": 2023,
    "doi": "10.1038/s42256-023-00716-3",
    "abstract": null,
    "added_at": "2026-04-06T19:46:09.882748+00:00",
    "added_by": "seed_loader"
  },
  {
    "id": "bartel_2019_tolerance_factor",
    "source_type": "journal_article",
    "title": "New tolerance factor to predict the stability of perovskite oxides and halides",
    "authors": "Bartel, C.J.; Sutton, C.; Goldsmith, B.R.; Ouyang, R.; Musgrave, C.B.; Ghiringhelli, L.M.; Scheffler, M.",
    "year": 2019,
    "doi": "10.1126/sciadv.aav0693",
    "abstract": null,
    "added_at": "2026-04-06T23:47:14.255910+00:00",
    "added_by": "seed_loader"
  },
  {
    "id": "szymanski_2023_autonomous_lab",
    "source_type": "journal_article",
    "title": "An autonomous laboratory for the accelerated synthesis of novel materials",
    "authors": "Szymanski, N.J.; Rendy, B.; Fei, Y.; Kumar, R.E.; He, T.; Milber, D.; Jiang, H.; Bartel, C.J.; et al.",
    "year": 2023,
    "doi": "10.1038/s41586-023-06734-w",
    "abstract": null,
    "added_at": "2026-04-06T23:47:14.272046+00:00",
    "added_by": "seed_loader"
  }
]